MANIFEST.in
README.rst
setup.py
weaklysupervised/BootstrappingSSL.py
weaklysupervised/__init__.py
weaklysupervised.egg-info/PKG-INFO
weaklysupervised.egg-info/SOURCES.txt
weaklysupervised.egg-info/dependency_links.txt
weaklysupervised.egg-info/requires.txt
weaklysupervised.egg-info/top_level.txt